[
  {
    "gemseo_variable": "wing_span",
    "size": 1,
    "cta_parameters": [
      "span"
    ],
    "units": "m",
    "normalization": "absolute",
    "description": "CTA outer semispan, i.e. wing span = B2 + B3.",
    "lower_bounds": [
      30.0
    ],
    "upper_bounds": [
      35.0
    ],
    "reference": [
      31.459
    ]
  },
  {
    "gemseo_variable": "c0_body_chord",
    "size": 1,
    "cta_parameters": [
      "c1_root_chord"
    ],
    "units": "m",
    "normalization": "absolute",
    "description": "CTA body chord C0.",
    "lower_bounds": [
      37.0
    ],
    "upper_bounds": [
      45.0
    ],
    "reference": [
      41.203
    ]
  },
  {
    "gemseo_variable": "c3_transition_chord",
    "size": 1,
    "cta_parameters": [
      "c2_c1_ratio"
    ],
    "units": "m",
    "normalization": "absolute",
    "description": "CTA transition-wing chord C3.",
    "lower_bounds": [
      13.0
    ],
    "upper_bounds": [
      16.0
    ],
    "reference": [
      13.927
    ]
  },
  {
    "gemseo_variable": "c4_outer_wing_chord",
    "size": 1,
    "cta_parameters": [
      "c3_c1_ratio"
    ],
    "units": "m",
    "normalization": "absolute",
    "description": "CTA outer-wing chord C4.",
    "lower_bounds": [
      6.8
    ],
    "upper_bounds": [
      9.8
    ],
    "reference": [
      7.768
    ]
  },
  {
    "gemseo_variable": "b2_wing_fraction",
    "size": 1,
    "cta_parameters": [
      "b2_span_ratio"
    ],
    "units": "-",
    "normalization": "fraction of wing span",
    "description": "CTA transition-wing fraction B2/(B2+B3).",
    "lower_bounds": [
      0.14
    ],
    "upper_bounds": [
      0.23
    ],
    "reference": [
      0.14202612924759211
    ]
  },
  {
    "gemseo_variable": "c5_wing_tip_chord",
    "size": 1,
    "cta_parameters": [
      "c4_c1_ratio"
    ],
    "units": "m",
    "normalization": "absolute",
    "description": "CTA wing-tip chord C5.",
    "lower_bounds": [
      0.8
    ],
    "upper_bounds": [
      1.8
    ],
    "reference": [
      0.8000000000000002
    ]
  },
  {
    "gemseo_variable": "sweeps_deg",
    "size": 2,
    "cta_parameters": [
      "s2_deg",
      "s3_deg"
    ],
    "units": "deg",
    "normalization": "angle",
    "description": "CTA public sweeps S1 and S2.",
    "lower_bounds": [
      45.0,
      27.0
    ],
    "upper_bounds": [
      66.0,
      40.0
    ],
    "reference": [
      54.059,
      27.71
    ]
  },
  {
    "gemseo_variable": "twist_deg",
    "size": 3,
    "cta_parameters": [
      "twist_c1_deg",
      "twist_c3_deg",
      "twist_c4_deg"
    ],
    "units": "deg",
    "normalization": "angle",
    "description": "Twist values at CTA sections C0/C3, C4 and C5.",
    "lower_bounds": [
      0.2,
      0.1,
      0.1
    ],
    "upper_bounds": [
      2.0,
      1.5,
      1.0
    ],
    "reference": [
      1.0,
      0.8,
      0.6
    ]
  },
  {
    "gemseo_variable": "c0_upper_cst",
    "size": 6,
    "cta_parameters": [
      "c1_upper_cst_0",
      "c1_upper_cst_1",
      "c1_upper_cst_2",
      "c1_upper_cst_3",
      "c1_upper_cst_4",
      "c1_upper_cst_5"
    ],
    "units": "-",
    "normalization": "Bernstein coefficient",
    "description": "Upper CST coefficients of CTA section C0.",
    "lower_bounds": [
      0.259394,
      0.28033889224031033,
      0.12007,
      0.1391377839598255,
      0.0461415925892451,
      0.0
    ],
    "upper_bounds": [
      0.39541086159348454,
      0.4601558612848153,
      0.42650346109126414,
      0.463723,
      0.127171540154187,
      0.362029
    ],
    "reference": [
      0.259394,
      0.305777,
      0.12007,
      0.463723,
      0.048878,
      0.362029
    ]
  },
  {
    "gemseo_variable": "c0_lower_cst",
    "size": 6,
    "cta_parameters": [
      "c1_lower_cst_0",
      "c1_lower_cst_1",
      "c1_lower_cst_2",
      "c1_lower_cst_3",
      "c1_lower_cst_4",
      "c1_lower_cst_5"
    ],
    "units": "-",
    "normalization": "Bernstein coefficient",
    "description": "Lower CST coefficients of CTA section C0.",
    "lower_bounds": [
      0.253318,
      0.18989915177521594,
      0.088106,
      0.10638503612510596,
      -0.0086,
      0.0
    ],
    "upper_bounds": [
      0.31782917696478785,
      0.3697161208197233,
      0.34511569097268746,
      0.393359,
      0.1252906680004572,
      0.294603
    ],
    "reference": [
      0.253318,
      0.231613,
      0.088106,
      0.393359,
      -0.0086,
      0.294603
    ]
  },
  {
    "gemseo_variable": "c3_upper_cst",
    "size": 6,
    "cta_parameters": [
      "c2_upper_cst_0",
      "c2_upper_cst_1",
      "c2_upper_cst_2",
      "c2_upper_cst_3",
      "c2_upper_cst_4",
      "c2_upper_cst_5"
    ],
    "units": "-",
    "normalization": "Bernstein coefficient",
    "description": "Upper CST coefficients of CTA section C3.",
    "lower_bounds": [
      0.23091,
      0.26198125957243457,
      0.108505,
      0.13793338073362493,
      0.04664,
      0.0
    ],
    "upper_bounds": [
      0.3789517653485678,
      0.4417982286169343,
      0.41428652304593144,
      0.416108,
      0.1291361350414658,
      0.325549
    ],
    "reference": [
      0.23091,
      0.275922,
      0.108505,
      0.416108,
      0.04664,
      0.325549
    ]
  },
  {
    "gemseo_variable": "c3_lower_cst",
    "size": 6,
    "cta_parameters": [
      "c2_lower_cst_0",
      "c2_lower_cst_1",
      "c2_lower_cst_2",
      "c2_lower_cst_3",
      "c2_lower_cst_4",
      "c2_lower_cst_5"
    ],
    "units": "-",
    "normalization": "Bernstein coefficient",
    "description": "Lower CST coefficients of CTA section C3.",
    "lower_bounds": [
      0.224834,
      0.17572063501945245,
      0.076541,
      0.0991903470916873,
      -0.010837,
      0.0
    ],
    "upper_bounds": [
      0.3044686146144233,
      0.3555376040639564,
      0.33176600355957425,
      0.345743,
      0.12343825262179095,
      0.258124
    ],
    "reference": [
      0.224834,
      0.201758,
      0.076541,
      0.345743,
      -0.010837,
      0.258124
    ]
  },
  {
    "gemseo_variable": "c4_upper_cst",
    "size": 6,
    "cta_parameters": [
      "c3_upper_cst_0",
      "c3_upper_cst_1",
      "c3_upper_cst_2",
      "c3_upper_cst_3",
      "c3_upper_cst_4",
      "c3_upper_cst_5"
    ],
    "units": "-",
    "normalization": "Bernstein coefficient",
    "description": "Upper CST coefficients of CTA section C4.",
    "lower_bounds": [
      0.202426,
      0.246067,
      0.096939,
      0.14278557733593522,
      0.044403,
      0.0
    ],
    "upper_bounds": [
      0.3655084503668841,
      0.4255625448772534,
      0.40714932156215494,
      0.368492,
      0.13239035255939696,
      0.28907
    ],
    "reference": [
      0.202426,
      0.246067,
      0.096939,
      0.368492,
      0.044403,
      0.28907
    ]
  },
  {
    "gemseo_variable": "c4_lower_cst",
    "size": 6,
    "cta_parameters": [
      "c3_lower_cst_0",
      "c3_lower_cst_1",
      "c3_lower_cst_2",
      "c3_lower_cst_3",
      "c3_lower_cst_4",
      "c3_lower_cst_5"
    ],
    "units": "-",
    "normalization": "Bernstein coefficient",
    "description": "Lower CST coefficients of CTA section C4.",
    "lower_bounds": [
      0.19635,
      0.1710498058099375,
      0.064976,
      0.09852258881212488,
      -0.013075,
      0.0
    ],
    "upper_bounds": [
      0.29128628786222366,
      0.3411630879650686,
      0.32390705192129726,
      0.298128,
      0.12191562665439477,
      0.221644
    ],
    "reference": [
      0.19635,
      0.171903,
      0.064976,
      0.298128,
      -0.013075,
      0.221644
    ]
  },
  {
    "gemseo_variable": "c5_upper_cst",
    "size": 6,
    "cta_parameters": [
      "c4_upper_cst_0",
      "c4_upper_cst_1",
      "c4_upper_cst_2",
      "c4_upper_cst_3",
      "c4_upper_cst_4",
      "c4_upper_cst_5"
    ],
    "units": "-",
    "normalization": "Bernstein coefficient",
    "description": "Upper CST coefficients of CTA section C5.",
    "lower_bounds": [
      0.173942,
      0.216212,
      0.085374,
      0.14278557733593122,
      0.042165,
      0.0
    ],
    "upper_bounds": [
      0.3655084503668841,
      0.42556254487725587,
      0.4071493215621568,
      0.320876,
      0.13239035255940002,
      0.25259
    ],
    "reference": [
      0.173942,
      0.216212,
      0.085374,
      0.320876,
      0.042165,
      0.25259
    ]
  },
  {
    "gemseo_variable": "c5_lower_cst",
    "size": 6,
    "cta_parameters": [
      "c4_lower_cst_0",
      "c4_lower_cst_1",
      "c4_lower_cst_2",
      "c4_lower_cst_3",
      "c4_lower_cst_4",
      "c4_lower_cst_5"
    ],
    "units": "-",
    "normalization": "Bernstein coefficient",
    "description": "Lower CST coefficients of CTA section C5.",
    "lower_bounds": [
      0.167866,
      0.142048,
      0.05341,
      0.09852258881212396,
      -0.015313,
      0.0
    ],
    "upper_bounds": [
      0.29128628786222366,
      0.34116308796506867,
      0.3239070519212976,
      0.2558822736719387,
      0.12191562665439479,
      0.185165
    ],
    "reference": [
      0.167866,
      0.142048,
      0.05341,
      0.250512,
      -0.015313,
      0.185165
    ]
  }
]